aoccasper/__init__.py
aoccasper/test.py
aoccasper/day1/__init__.py
aoccasper/day1/main.py
aoccasper/day2/__init__.py
aoccasper/day2/main.py
aoccasper/day3/__init__.py
aoccasper/day3/main.py
aoccasper/utils/__init__.py
aoccasper/utils/autoinput.py
aoccasper/utils/session_cookies_handler.py
aoccasper-0.0.2.dist-info/METADATA
aoccasper-0.0.2.dist-info/WHEEL
aoccasper-0.0.2.dist-info/top_level.txt
aoccasper-0.0.2.dist-info/RECORD
