Metadata-Version: 2.1
Name: aoccasper
Version: 0.0.2
Author: Casper Chris Adriaan Bekkers
Author-email: casperbekkers@hotmail.com
Requires-Dist: requests
